<?xml version="1.0" encoding="utf-8"?>
<KeyInfo>
    <!-- 分享平台的注册信息，一定要填入在相应平台注册的正确信息，不然应用无法完成授权，  也无法进行分享，enable填写true或者false属性决定是否分享该平台-->
    <!-- 友推sdk注册地址 : http://youtui.mobi/ -->
    <YouTui AppKey="875083" />

    <!-- 微信和朋友圈注册:https://open.weixin.qq.com/ -->
    <Wechat AppId="wx5807c8d8d9cbe4a8" Enable="true" />
    <WechatMoments AppId="wx5807c8d8d9cbe4a8" Enable="true" />

    <!-- 新浪微博注册地址:http://open.weibo.com/ -->
    <!-- IsNoKeyShare属性,如果开发者没有新浪微博的key但是希望能使用新浪微博的分享功能,可以将IsNoKeyShare设置为true,这样就不需要设置AppKey,AppSecret,RedirectUrl而是使用友推默认的新浪注册信息 -->
    <!-- IsWebShare设置为true则使用web分享而不是使用默认的调用新浪微博客户端进行分享,有用户在小米等机型下调用新浪微博客户端进行分享时无法获得授权,这样的话请使用web方式进行分享 -->
    <SinaWeibo IsNoKeyShare="false" IsWebShare="true" AppKey="3851387912" AppSecret="51b6cd0b3776d9aaafebdfc7f74d7d6f" Enable="true" RedirectUrl="http://joke.realityandapp.com/users/auth/weibo/callback" />

    <!-- QQ,QQ空间,腾讯微博注册地址:http://open.qq.com/ -->
    <QQ AppId="" AppKey="" Enable="" />
    <QZone AppId="" AppKey="" Enable="" />
    <!-- 腾讯微博注册地址:http://dev.t.qq.com/ -->
    <!-- IsNoKeyShare属性,如果开发者没有腾讯微博的key但是希望能使用腾讯微博的分享功能,可以将IsNoKeyShare设置为true,这样就不需要设置AppKey,AppSecret,RedirectUrl而是使用友推默认的腾讯微博注册信息 -->
    <TencentWeibo IsNoKeyShare="true" AppKey="" AppSecret="" Enable="true" RedirectUrl="" />

    <!-- 人人注册地址: http://dev.renren.com/ -->
    <Renren AppKey="" AppId="" Enable="" SecretKey="" />
    <ShortMessage Enable="true" />
    <Email Enable="true" />
    <!-- 复制链接 -->
    <CopyLink Enable="true"/>
    <!-- 调用系统分享，适用于暂时没有申请到key的分享，该分享不会获得积分，也不会被统计到 -->
    <More Enable="true"/>
</KeyInfo>